LICENSE
MANIFEST.in
README.md
requirements.txt
setup.cfg
setup.py
exabgpctl/__init__.py
exabgpctl/_py6.py
exabgpctl/controller.py
exabgpctl/release.py
exabgpctl/view.py
exabgpctl.egg-info/PKG-INFO
exabgpctl.egg-info/SOURCES.txt
exabgpctl.egg-info/dependency_links.txt
exabgpctl.egg-info/entry_points.txt
exabgpctl.egg-info/requires.txt
exabgpctl.egg-info/top_level.txt