Metadata-Version: 2.1
Name: exabgpctl
Version: 19.6.post1
Summary: ExaBGP admin CLI
Home-page: https://github.com/ahmet2mir/exabgpctl.git
Author: Ahmet Demir
Author-email: me@ahmet2mir.eu
License: Apache 2.0
Keywords: exabgpctl,command line,cli,ssh,r10k
Platform: UNKNOWN
Classifier: Development Status :: 2 - Pre-Alpha
Classifier: Intended Audience :: Developers
Classifier: License :: OSI Approved :: Apache Software License
Classifier: Operating System :: OS Independent
Classifier: Programming Language :: Python
Classifier: Programming Language :: Python :: 2.7
Classifier: Programming Language :: Python :: 3.4
Classifier: Programming Language :: Python :: 3.5
Classifier: Programming Language :: Python :: 3.6
Classifier: Programming Language :: Python :: 3.7
Classifier: Topic :: Software Development :: Build Tools
Requires-Python: >=2.7,!=3.0.*,!=3.1.*,!=3.2.*,!=3.3.*
